sam2fasta/__init__.py
sam2fasta/sam2fasta.py
sam2fasta-0.1.0.dist-info/DESCRIPTION.rst
sam2fasta-0.1.0.dist-info/METADATA
sam2fasta-0.1.0.dist-info/RECORD
sam2fasta-0.1.0.dist-info/WHEEL
sam2fasta-0.1.0.dist-info/entry_points.txt
sam2fasta-0.1.0.dist-info/metadata.json
sam2fasta-0.1.0.dist-info/top_level.txt
sam2fasta-0.1.0.dist-info/zip-safe
