Metadata-Version: 2.0
Name: sam2fasta
Version: 0.1.0
Summary: Simple script to convert sam file to fasta format.
Home-page: https://github.com/mhozza/sam2fasta
Author: Michal Hozza
Author-email: mhozza@gmail.com
License: ISCL
Keywords: sam2fasta
Platform: UNKNOWN
Classifier: Development Status :: 4 - Beta
Classifier: Environment :: Console
Classifier: Intended Audience :: Science/Research
Classifier: License :: OSI Approved :: ISC License (ISCL)
Classifier: Natural Language :: English
Classifier: Programming Language :: Python :: 2
Classifier: Programming Language :: Python :: 2.7
Classifier: Programming Language :: Python :: 3
Classifier: Programming Language :: Python :: 3.3
Classifier: Programming Language :: Python :: 3.4
Classifier: Programming Language :: Python :: 3.5
Classifier: Topic :: Scientific/Engineering :: Bio-Informatics
Requires-Dist: biopython
Requires-Dist: pysam
